setup.py
nessus/__init__.py
nessus/common.py
nessus/utils.py
nessus.egg-info/PKG-INFO
nessus.egg-info/SOURCES.txt
nessus.egg-info/dependency_links.txt
nessus.egg-info/not-zip-safe
nessus.egg-info/top_level.txt
tests/__init__.py
tests/test_nessus.py