Metadata-Version: 1.0
Name: nessus
Version: 0.0.1
Summary: Nessus XMLrpc interface
Home-page: http://digitsecurity.github.com/python-nessus/
Author: Alfred Hall
Author-email: ahall@ahall.org
License: UNKNOWN
Platform: UNKNOWN
